oleo/__init__.py
oleo/_version.py
oleo/example.py
oleo/gine_widget.py
oleo/netlist_graph.py
oleo/utils.py
oleo/labextension/package.json
oleo/labextension/static/164.60e63ba5c2547bbd9cc2.js
oleo/labextension/static/57.34bbb9856ab80fc79b34.js
oleo/labextension/static/908.1ee4013bf3ed59f7290e.js
oleo/labextension/static/remoteEntry.b81fb84b8e3f22fe8612.js
oleo/labextension/static/style.js
oleo/labextension/static/third-party-licenses.json
oleo/nbextension/extension.js
oleo/nbextension/index.js
oleo-0.0.9.data/data/share/jupyter/labextensions/oleo/install.json
oleo-0.0.9.data/data/share/jupyter/labextensions/oleo/package.json
oleo-0.0.9.data/data/share/jupyter/labextensions/oleo/static/164.60e63ba5c2547bbd9cc2.js
oleo-0.0.9.data/data/share/jupyter/labextensions/oleo/static/57.34bbb9856ab80fc79b34.js
oleo-0.0.9.data/data/share/jupyter/labextensions/oleo/static/908.1ee4013bf3ed59f7290e.js
oleo-0.0.9.data/data/share/jupyter/labextensions/oleo/static/remoteEntry.b81fb84b8e3f22fe8612.js
oleo-0.0.9.data/data/share/jupyter/labextensions/oleo/static/style.js
oleo-0.0.9.data/data/share/jupyter/labextensions/oleo/static/third-party-licenses.json
oleo-0.0.9.data/data/share/jupyter/nbextensions/oleo/extension.js
oleo-0.0.9.data/data/share/jupyter/nbextensions/oleo/index.js
oleo-0.0.9.dist-info/METADATA
oleo-0.0.9.dist-info/WHEEL
oleo-0.0.9.dist-info/top_level.txt
oleo-0.0.9.dist-info/RECORD
